{"id":11493495,"resource_state":3,"name":"Above LDC - East to West","activity_type":"Run","distance":1141.3,"average_grade":1.0,"maximum_grade":16.9,"elevation_high":278.4,"elevation_low":250.6,"start_latlng":[36.010341,-84.162937],"end_latlng":[36.009396,-84.170736],"start_latitude":36.010341,"start_longitude":-84.162937,"end_latitude":36.009396,"end_longitude":-84.170736,"climb_category":0,"city":"Oak Ridge","state":"Tennessee","country":"United States","private":false,"hazardous":false,"starred":false,"created_at":"2016-03-02T23:25:40Z","updated_at":"2016-07-08T08:05:29Z","total_elevation_gain":27.8,"map":{"id":"s11493495","polyline":"sgxzEjau`Or@Pk@PSN]\\e@T]XAB@Dj@r@z@r@An@T~@LPl@l@PLb@H^V~@b@\\^Or@`@r@Gv@Tb@RT~@PjALDNQj@[b@Ln@Ih@Qf@Fb@E|@Xl@NTLd@?ZHN\\ZDFKj@[`@a@JcABYHWLINB^EXQOe@CMJYd@Gb@@D","resource_state":3},"effort_count":32,"athlete_count":19,"star_count":0,"athlete_segment_stats":{"pr_elapsed_time":409,"pr_date":"2016-05-09","effort_count":3}}